pyproject.toml
setup.cfg
setup.py
src/apm_client/__init__.py
src/apm_client/attack.py
src/apm_client/bottle.py
src/apm_client/celery.py
src/apm_client/cherrypy.py
src/apm_client/compat.py
src/apm_client/dramatiq.py
src/apm_client/falcon.py
src/apm_client/huey.py
src/apm_client/hug.py
src/apm_client/nameko.py
src/apm_client/pyramid.py
src/apm_client/rq.py
src/apm_client/setup.py
src/apm_client/sqlalchemy.py
src/apm_client.egg-info/PKG-INFO
src/apm_client.egg-info/SOURCES.txt
src/apm_client.egg-info/dependency_links.txt
src/apm_client.egg-info/entry_points.txt
src/apm_client.egg-info/not-zip-safe
src/apm_client.egg-info/requires.txt
src/apm_client.egg-info/top_level.txt
src/apm_client/api/__init__.py
src/apm_client/async_/__init__.py
src/apm_client/async_/api.py
src/apm_client/async_/starlette.py
src/apm_client/async_/instruments/__init__.py
src/apm_client/async_/instruments/jinja2.py
src/apm_client/core/__init__.py
src/apm_client/core/_objtrace.c
src/apm_client/core/backtrace.py
src/apm_client/core/config.py
src/apm_client/core/context.py
src/apm_client/core/error.py
src/apm_client/core/error_service.py
src/apm_client/core/metadata.py
src/apm_client/core/n_plus_one_tracker.py
src/apm_client/core/objtrace.py
src/apm_client/core/platform_detection.py
src/apm_client/core/stacktracer.py
src/apm_client/core/threading.py
src/apm_client/core/tracked_request.py
src/apm_client/core/web_requests.py
src/apm_client/core/agent/__init__.py
src/apm_client/core/agent/commands.py
src/apm_client/core/agent/manager.py
src/apm_client/core/agent/socket.py
src/apm_client/core/cli/__init__.py
src/apm_client/core/cli/core_agent_manager.py
src/apm_client/core/local/__init__.py
src/apm_client/core/local/parse.py
src/apm_client/core/local/main/__init__.py
src/apm_client/core/local/main/base_core.py
src/apm_client/core/local/main/commons.py
src/apm_client/core/local/main/core.py
src/apm_client/core/samplers/__init__.py
src/apm_client/core/samplers/cpu.py
src/apm_client/core/samplers/memory.py
src/apm_client/core/samplers/thread.py
src/apm_client/django/__init__.py
src/apm_client/django/apps.py
src/apm_client/django/middleware.py
src/apm_client/django/request.py
src/apm_client/django/instruments/__init__.py
src/apm_client/django/instruments/huey.py
